odoo/addons/fieldservice_delivery_quantities/README.rst
odoo/addons/fieldservice_delivery_quantities/__init__.py
odoo/addons/fieldservice_delivery_quantities/__manifest__.py
odoo/addons/fieldservice_delivery_quantities/i18n/ca.po
odoo/addons/fieldservice_delivery_quantities/i18n/es.po
odoo/addons/fieldservice_delivery_quantities/i18n/fieldservice_delivery_quantities.pot
odoo/addons/fieldservice_delivery_quantities/models/__init__.py
odoo/addons/fieldservice_delivery_quantities/models/stock_move.py
odoo/addons/fieldservice_delivery_quantities/readme/CONTRIBUTORS.rst
odoo/addons/fieldservice_delivery_quantities/readme/DESCRIPTION.rst
odoo/addons/fieldservice_delivery_quantities/readme/USAGE.rst
odoo/addons/fieldservice_delivery_quantities/security/ir_rule.xml
odoo/addons/fieldservice_delivery_quantities/static/description/icon.png
odoo/addons/fieldservice_delivery_quantities/static/description/index.html
odoo/addons/fieldservice_delivery_quantities/views/menu.xml
odoo/addons/fieldservice_delivery_quantities/views/stock_move_views.xml
odoo_addon_fieldservice_delivery_quantities-15.0.1.0.0.2.dist-info/METADATA
odoo_addon_fieldservice_delivery_quantities-15.0.1.0.0.2.dist-info/WHEEL
odoo_addon_fieldservice_delivery_quantities-15.0.1.0.0.2.dist-info/top_level.txt
odoo_addon_fieldservice_delivery_quantities-15.0.1.0.0.2.dist-info/RECORD
